awoc/__init__.py
awoc/data/world.json
a_world_of_countries-1.0.0.dist-info/LICENSE
a_world_of_countries-1.0.0.dist-info/METADATA
a_world_of_countries-1.0.0.dist-info/WHEEL
a_world_of_countries-1.0.0.dist-info/top_level.txt
a_world_of_countries-1.0.0.dist-info/RECORD
