Metadata-Version: 2.1
Name: a-world-of-countries
Version: 1.0.0
Summary: A World of Countries (AWOC) is a fully-featured library that provides an easy layer to access mutiple data about world continents and countries, according to the ISO Standard 3166-1.
Home-page: https://github.com/lucagrandicelli/a-world-of-countries-py
Author: Luca Grandicelli
Author-email: luca.grandicelli79@gmail.com
License: UNKNOWN
Keywords: geography countries countries-api geography-database world languages currency country country-names country-codes
Platform: UNKNOWN
Classifier: Programming Language :: Python :: 3
Classifier: Programming Language :: Python :: 3.7
Classifier: License :: OSI Approved :: MIT License
Classifier: Operating System :: OS Independent
Classifier: Topic :: Utilities
Requires-Dist: pydash
